pyllama2/__init__.py
pyllama2-0.0.1.dev0.dist-info/METADATA
pyllama2-0.0.1.dev0.dist-info/WHEEL
pyllama2-0.0.1.dev0.dist-info/top_level.txt
pyllama2-0.0.1.dev0.dist-info/RECORD
