Metadata-Version: 2.1
Name: pyllama2
Version: 0.0.1.dev0
Summary: pyllama2
Author: juncongmoo
Keywords: pyllama2
Classifier: Programming Language :: Python :: 3
Classifier: Programming Language :: Python :: 3.8
Classifier: Programming Language :: Python :: 3.9
Classifier: Programming Language :: Python :: 3.10
Requires-Dist: torch
